fastapi_cdn_host-0.9.3.dist-info/METADATA
fastapi_cdn_host-0.9.3.dist-info/WHEEL
fastapi_cdn_host-0.9.3.dist-info/entry_points.txt
fastapi_cdn_host-0.9.3.dist-info/licenses/LICENSE
fastapi_cdn_host/__init__.py
fastapi_cdn_host/__main__.py
fastapi_cdn_host/cli.py
fastapi_cdn_host/client.py
fastapi_cdn_host/py.typed
fastapi_cdn_host/utils.py
fastapi_cdn_host-0.9.3.dist-info/RECORD
