Metadata-Version: 2.1
Name: fastapi-cdn-host
Version: 0.9.3
Summary: Auto choose the fastest cdn host for fastapi project docs.
Author-Email: Waket Zheng <waketzheng@gmail.com>
License: MIT
Project-URL: homepage, https://github.com/waketzheng/fastapi-cdn-host
Project-URL: repository, https://github.com/waketzheng/fastapi-cdn-host.git
Requires-Python: >=3.9
Requires-Dist: fastapi<1.0.0,>=0.110.0
Requires-Dist: httpx<1.0.0,>=0.23.0
Requires-Dist: eval-type-backport<0.3.0,>=0.2.2; python_version < "3.10"
Provides-Extra: cli
Requires-Dist: typer>=0.15.2; extra == "cli"
Provides-Extra: all
Requires-Dist: fastapi-cli>=0.0.7; extra == "all"
